chty/__init__.py
chty/cli.py
chty/codegen.py
chty/parser.py
chty/schema.py
chty/typemapper.py
chty/validator.py
chty-0.1.2.dist-info/METADATA
chty-0.1.2.dist-info/WHEEL
chty-0.1.2.dist-info/entry_points.txt
chty-0.1.2.dist-info/licenses/LICENSE
chty-0.1.2.dist-info/RECORD
