Metadata-Version: 2.4
Name: chty
Version: 0.1.2
Summary: Type-safe ClickHouse query parameter codegen from SQL files
License-File: LICENSE
Requires-Python: >=3.10
Requires-Dist: clickhouse-connect>=0.9.2
Requires-Dist: pandas>=2.0.0
Requires-Dist: typer>=0.9.0
Provides-Extra: dev
Requires-Dist: pytest>=7.0.0; extra == 'dev'
Provides-Extra: docs
Requires-Dist: mkdocs-material>=9.4.0; extra == 'docs'
Requires-Dist: mkdocs>=1.5.0; extra == 'docs'
Requires-Dist: pymdown-extensions>=10.0.0; extra == 'docs'
